{"aiohttp/setup.py": {"loc": 126, "lloc": 38, "sloc": 106, "comments": 2, "multi": 0, "blank": 19, "single_comments": 1}, "aiohttp/examples/web_cookies.py": {"loc": 45, "lloc": 23, "sloc": 29, "comments": 1, "multi": 2, "blank": 13, "single_comments": 1}, "aiohttp/examples/server_simple.py": {"loc": 31, "lloc": 19, "sloc": 21, "comments": 1, "multi": 0, "blank": 9, "single_comments": 1}, "aiohttp/examples/cli_app.py": {"loc": 55, "lloc": 17, "sloc": 27, "comments": 3, "multi": 10, "blank": 15, "single_comments": 3}, "aiohttp/examples/web_srv_route_deco.py": {"loc": 60, "lloc": 39, "sloc": 41, "comments": 1, "multi": 3, "blank": 15, "single_comments": 1}, "aiohttp/examples/background_tasks.py": {"loc": 65, "lloc": 48, "sloc": 47, "comments": 2, "multi": 0, "blank": 15, "single_comments": 3}, "aiohttp/examples/web_classview.py": {"loc": 57, "lloc": 22, "sloc": 41, "comments": 1, "multi": 2, "blank": 13, "single_comments": 1}, "aiohttp/examples/lowlevel_srv.py": {"loc": 26, "lloc": 15, "sloc": 15, "comments": 2, "multi": 0, "blank": 9, "single_comments": 2}, "aiohttp/examples/web_srv.py": {"loc": 57, "lloc": 38, "sloc": 40, "comments": 1, "multi": 2, "blank": 14, "single_comments": 1}, "aiohttp/examples/client_ws.py": {"loc": 71, "lloc": 49, "sloc": 53, "comments": 3, "multi": 0, "blank": 14, "single_comments": 4}, "aiohttp/examples/client_json.py": {"loc": 22, "lloc": 14, "sloc": 15, "comments": 0, "multi": 0, "blank": 7, "single_comments": 0}, "aiohttp/examples/curl.py": {"loc": 31, "lloc": 20, "sloc": 22, "comments": 1, "multi": 0, "blank": 8, "single_comments": 1}, "aiohttp/examples/web_ws.py": {"loc": 58, "lloc": 40, "sloc": 39, "comments": 1, "multi": 2, "blank": 16, "single_comments": 1}, "aiohttp/examples/client_auth.py": {"loc": 22, "lloc": 13, "sloc": 15, "comments": 0, "multi": 0, "blank": 7, "single_comments": 0}, "aiohttp/examples/web_rewrite_headers_middleware.py": {"loc": 29, "lloc": 17, "sloc": 16, "comments": 1, "multi": 3, "blank": 9, "single_comments": 1}, "aiohttp/examples/web_srv_route_table.py": {"loc": 60, "lloc": 34, "sloc": 42, "comments": 1, "multi": 3, "blank": 14, "single_comments": 1}, "aiohttp/examples/static_files.py": {"loc": 8, "lloc": 5, "sloc": 5, "comments": 0, "multi": 0, "blank": 3, "single_comments": 0}, "aiohttp/examples/fake_server.py": {"loc": 115, "lloc": 62, "sloc": 94, "comments": 0, "multi": 0, "blank": 20, "single_comments": 1}, "aiohttp/examples/legacy/crawl.py": {"loc": 100, "lloc": 74, "sloc": 78, "comments": 2, "multi": 0, "blank": 20, "single_comments": 2}, "aiohttp/examples/legacy/tcp_protocol_parser.py": {"loc": 176, "lloc": 115, "sloc": 123, "comments": 4, "multi": 8, "blank": 40, "single_comments": 5}, "aiohttp/examples/legacy/srv.py": {"loc": 165, "lloc": 116, "sloc": 130, "comments": 5, "multi": 0, "blank": 30, "single_comments": 5}, "aiohttp/docs/conf.py": {"loc": 336, "lloc": 40, "sloc": 112, "comments": 157, "multi": 0, "blank": 74, "single_comments": 150}, "aiohttp/aiohttp/formdata.py": {"loc": 154, "lloc": 100, "sloc": 120, "comments": 7, "multi": 2, "blank": 28, "single_comments": 4}, "aiohttp/aiohttp/web_app.py": {"loc": 390, "lloc": 242, "sloc": 298, "comments": 27, "multi": 9, "blank": 72, "single_comments": 11}, "aiohttp/aiohttp/web_exceptions.py": {"loc": 494, "lloc": 214, "sloc": 312, "comments": 27, "multi": 0, "blank": 154, "single_comments": 28}, "aiohttp/aiohttp/hdrs.py": {"loc": 100, "lloc": 91, "sloc": 91, "comments": 2, "multi": 0, "blank": 6, "single_comments": 3}, "aiohttp/aiohttp/web_urldispatcher.py": {"loc": 1123, "lloc": 724, "sloc": 811, "comments": 47, "multi": 45, "blank": 237, "single_comments": 30}, "aiohttp/aiohttp/web_protocol.py": {"loc": 656, "lloc": 366, "sloc": 467, "comments": 40, "multi": 51, "blank": 111, "single_comments": 27}, "aiohttp/aiohttp/web_response.py": {"loc": 720, "lloc": 470, "sloc": 561, "comments": 48, "multi": 10, "blank": 120, "single_comments": 29}, "aiohttp/aiohttp/tcp_helpers.py": {"loc": 63, "lloc": 40, "sloc": 42, "comments": 8, "multi": 0, "blank": 19, "single_comments": 2}, "aiohttp/aiohttp/tracing.py": {"loc": 387, "lloc": 199, "sloc": 292, "comments": 20, "multi": 4, "blank": 75, "single_comments": 16}, "aiohttp/aiohttp/web.py": {"loc": 515, "lloc": 223, "sloc": 479, "comments": 27, "multi": 0, "blank": 31, "single_comments": 5}, "aiohttp/aiohttp/streams.py": {"loc": 622, "lloc": 411, "sloc": 412, "comments": 56, "multi": 30, "blank": 140, "single_comments": 40}, "aiohttp/aiohttp/client_ws.py": {"loc": 308, "lloc": 217, "sloc": 255, "comments": 12, "multi": 0, "blank": 46, "single_comments": 7}, "aiohttp/aiohttp/frozenlist.py": {"loc": 72, "lloc": 51, "sloc": 52, "comments": 3, "multi": 0, "blank": 20, "single_comments": 0}, "aiohttp/aiohttp/web_server.py": {"loc": 63, "lloc": 37, "sloc": 51, "comments": 2, "multi": 0, "blank": 11, "single_comments": 1}, "aiohttp/aiohttp/payload.py": {"loc": 456, "lloc": 240, "sloc": 344, "comments": 17, "multi": 6, "blank": 94, "single_comments": 12}, "aiohttp/aiohttp/signals.py": {"loc": 34, "lloc": 16, "sloc": 16, "comments": 1, "multi": 8, "blank": 10, "single_comments": 0}, "aiohttp/aiohttp/web_routedef.py": {"loc": 202, "lloc": 115, "sloc": 143, "comments": 10, "multi": 0, "blank": 58, "single_comments": 1}, "aiohttp/aiohttp/client_reqrep.py": {"loc": 994, "lloc": 653, "sloc": 774, "comments": 105, "multi": 3, "blank": 161, "single_comments": 56}, "aiohttp/aiohttp/http_writer.py": {"loc": 172, "lloc": 114, "sloc": 117, "comments": 6, "multi": 10, "blank": 42, "single_comments": 3}, "aiohttp/aiohttp/web_ws.py": {"loc": 465, "lloc": 323, "sloc": 382, "comments": 27, "multi": 0, "blank": 69, "single_comments": 14}, "aiohttp/aiohttp/web_runner.py": {"loc": 372, "lloc": 238, "sloc": 288, "comments": 23, "multi": 0, "blank": 74, "single_comments": 10}, "aiohttp/aiohttp/web_fileresponse.py": {"loc": 372, "lloc": 197, "sloc": 257, "comments": 70, "multi": 0, "blank": 55, "single_comments": 60}, "aiohttp/aiohttp/web_log.py": {"loc": 237, "lloc": 106, "sloc": 153, "comments": 7, "multi": 41, "blank": 39, "single_comments": 4}, "aiohttp/aiohttp/worker.py": {"loc": 231, "lloc": 138, "sloc": 159, "comments": 25, "multi": 3, "blank": 55, "single_comments": 14}, "aiohttp/aiohttp/base_protocol.py": {"loc": 81, "lloc": 66, "sloc": 67, "comments": 4, "multi": 0, "blank": 13, "single_comments": 1}, "aiohttp/aiohttp/test_utils.py": {"loc": 668, "lloc": 361, "sloc": 439, "comments": 17, "multi": 70, "blank": 140, "single_comments": 19}, "aiohttp/aiohttp/connector.py": {"loc": 1169, "lloc": 680, "sloc": 821, "comments": 88, "multi": 90, "blank": 191, "single_comments": 67}, "aiohttp/aiohttp/client.py": {"loc": 1164, "lloc": 527, "sloc": 899, "comments": 71, "multi": 54, "blank": 142, "single_comments": 69}, "aiohttp/aiohttp/log.py": {"loc": 8, "lloc": 7, "sloc": 7, "comments": 0, "multi": 0, "blank": 1, "single_comments": 0}, "aiohttp/aiohttp/__init__.py": {"loc": 224, "lloc": 97, "sloc": 220, "comments": 15, "multi": 0, "blank": 4, "single_comments": 0}, "aiohttp/aiohttp/http_exceptions.py": {"loc": 108, "lloc": 56, "sloc": 58, "comments": 0, "multi": 6, "blank": 39, "single_comments": 5}, "aiohttp/aiohttp/client_exceptions.py": {"loc": 266, "lloc": 141, "sloc": 146, "comments": 11, "multi": 19, "blank": 82, "single_comments": 19}, "aiohttp/aiohttp/http.py": {"loc": 50, "lloc": 29, "sloc": 42, "comments": 6, "multi": 0, "blank": 8, "single_comments": 0}, "aiohttp/aiohttp/resolver.py": {"loc": 79, "lloc": 46, "sloc": 53, "comments": 2, "multi": 3, "blank": 21, "single_comments": 2}, "aiohttp/aiohttp/multipart.py": {"loc": 1018, "lloc": 659, "sloc": 743, "comments": 77, "multi": 39, "blank": 167, "single_comments": 69}, "aiohttp/aiohttp/typedefs.py": {"loc": 63, "lloc": 33, "sloc": 56, "comments": 4, "multi": 0, "blank": 7, "single_comments": 0}, "aiohttp/aiohttp/locks.py": {"loc": 44, "lloc": 31, "sloc": 29, "comments": 3, "multi": 5, "blank": 9, "single_comments": 1}, "aiohttp/aiohttp/abc.py": {"loc": 213, "lloc": 126, "sloc": 116, "comments": 9, "multi": 12, "blank": 57, "single_comments": 28}, "aiohttp/aiohttp/pytest_plugin.py": {"loc": 322, "lloc": 191, "sloc": 209, "comments": 45, "multi": 29, "blank": 69, "single_comments": 15}, "aiohttp/aiohttp/http_websocket.py": {"loc": 654, "lloc": 419, "sloc": 475, "comments": 60, "multi": 11, "blank": 110, "single_comments": 58}, "aiohttp/aiohttp/client_proto.py": {"loc": 246, "lloc": 158, "sloc": 179, "comments": 24, "multi": 0, "blank": 47, "single_comments": 20}, "aiohttp/aiohttp/web_middlewares.py": {"loc": 124, "lloc": 60, "sloc": 71, "comments": 3, "multi": 23, "blank": 30, "single_comments": 0}, "aiohttp/aiohttp/http_parser.py": {"loc": 795, "lloc": 498, "sloc": 597, "comments": 73, "multi": 14, "blank": 129, "single_comments": 55}, "aiohttp/aiohttp/web_request.py": {"loc": 783, "lloc": 466, "sloc": 529, "comments": 44, "multi": 79, "blank": 137, "single_comments": 38}, "aiohttp/aiohttp/cookiejar.py": {"loc": 367, "lloc": 249, "sloc": 268, "comments": 20, "multi": 3, "blank": 79, "single_comments": 17}, "aiohttp/aiohttp/helpers.py": {"loc": 723, "lloc": 447, "sloc": 508, "comments": 46, "multi": 23, "blank": 162, "single_comments": 30}, "aiohttp/tests/test_client_exceptions.py": {"loc": 267, "lloc": 171, "sloc": 226, "comments": 1, "multi": 0, "blank": 40, "single_comments": 1}, "aiohttp/tests/test_web_functional.py": {"loc": 1925, "lloc": 1351, "sloc": 1393, "comments": 16, "multi": 0, "blank": 517, "single_comments": 15}, "aiohttp/tests/test_helpers.py": {"loc": 598, "lloc": 388, "sloc": 423, "comments": 21, "multi": 0, "blank": 154, "single_comments": 21}, "aiohttp/tests/test_signals.py": {"loc": 167, "lloc": 113, "sloc": 112, "comments": 0, "multi": 0, "blank": 55, "single_comments": 0}, "aiohttp/tests/test_web_cli.py": {"loc": 143, "lloc": 75, "sloc": 101, "comments": 0, "multi": 0, "blank": 42, "single_comments": 0}, "aiohttp/tests/test_http_exceptions.py": {"loc": 149, "lloc": 107, "sloc": 122, "comments": 1, "multi": 0, "blank": 26, "single_comments": 1}, "aiohttp/tests/test_web_exceptions.py": {"loc": 309, "lloc": 238, "sloc": 253, "comments": 0, "multi": 0, "blank": 56, "single_comments": 0}, "aiohttp/tests/test_streams.py": {"loc": 1355, "lloc": 964, "sloc": 970, "comments": 58, "multi": 0, "blank": 330, "single_comments": 55}, "aiohttp/tests/test_web_urldispatcher.py": {"loc": 409, "lloc": 228, "sloc": 265, "comments": 37, "multi": 0, "blank": 106, "single_comments": 38}, "aiohttp/tests/test_client_ws.py": {"loc": 694, "lloc": 427, "sloc": 560, "comments": 5, "multi": 0, "blank": 129, "single_comments": 5}, "aiohttp/tests/test_frozenlist.py": {"loc": 228, "lloc": 178, "sloc": 178, "comments": 0, "multi": 0, "blank": 50, "single_comments": 0}, "aiohttp/tests/test_classbasedview.py": {"loc": 55, "lloc": 39, "sloc": 39, "comments": 0, "multi": 0, "blank": 16, "single_comments": 0}, "aiohttp/tests/test_locks.py": {"loc": 55, "lloc": 39, "sloc": 39, "comments": 1, "multi": 0, "blank": 15, "single_comments": 1}, "aiohttp/tests/test_web_request_handler.py": {"loc": 61, "lloc": 40, "sloc": 40, "comments": 0, "multi": 0, "blank": 21, "single_comments": 0}, "aiohttp/tests/test_tcp_helpers.py": {"loc": 144, "lloc": 98, "sloc": 108, "comments": 6, "multi": 0, "blank": 30, "single_comments": 6}, "aiohttp/tests/test_client_connection.py": {"loc": 133, "lloc": 96, "sloc": 96, "comments": 1, "multi": 0, "blank": 37, "single_comments": 0}, "aiohttp/tests/test_web_protocol.py": {"loc": 896, "lloc": 508, "sloc": 644, "comments": 13, "multi": 0, "blank": 240, "single_comments": 12}, "aiohttp/tests/test_loop.py": {"loc": 39, "lloc": 25, "sloc": 28, "comments": 0, "multi": 0, "blank": 11, "single_comments": 0}, "aiohttp/tests/test_client_proto.py": {"loc": 132, "lloc": 89, "sloc": 96, "comments": 1, "multi": 0, "blank": 35, "single_comments": 1}, "aiohttp/tests/test_web_server.py": {"loc": 187, "lloc": 114, "sloc": 137, "comments": 2, "multi": 0, "blank": 48, "single_comments": 2}, "aiohttp/tests/test_web_app.py": {"loc": 457, "lloc": 338, "sloc": 340, "comments": 0, "multi": 0, "blank": 117, "single_comments": 0}, "aiohttp/tests/test_proxy.py": {"loc": 571, "lloc": 296, "sloc": 481, "comments": 7, "multi": 0, "blank": 83, "single_comments": 7}, "aiohttp/tests/test_web_request.py": {"loc": 801, "lloc": 557, "sloc": 590, "comments": 13, "multi": 0, "blank": 199, "single_comments": 12}, "aiohttp/tests/test_worker.py": {"loc": 288, "lloc": 196, "sloc": 216, "comments": 4, "multi": 0, "blank": 70, "single_comments": 2}, "aiohttp/tests/test_web_websocket_functional.py": {"loc": 836, "lloc": 588, "sloc": 593, "comments": 5, "multi": 0, "blank": 239, "single_comments": 4}, "aiohttp/tests/test_formdata.py": {"loc": 101, "lloc": 68, "sloc": 70, "comments": 1, "multi": 0, "blank": 31, "single_comments": 0}, "aiohttp/tests/test_http_writer.py": {"loc": 211, "lloc": 132, "sloc": 155, "comments": 1, "multi": 0, "blank": 55, "single_comments": 1}, "aiohttp/tests/test_route_def.py": {"loc": 320, "lloc": 210, "sloc": 210, "comments": 2, "multi": 0, "blank": 110, "single_comments": 0}, "aiohttp/tests/test_client_fingerprint.py": {"loc": 34, "lloc": 23, "sloc": 23, "comments": 0, "multi": 0, "blank": 11, "single_comments": 0}, "aiohttp/tests/test_test_utils.py": {"loc": 319, "lloc": 219, "sloc": 235, "comments": 3, "multi": 0, "blank": 81, "single_comments": 3}, "aiohttp/tests/test_flowcontrol_streams.py": {"loc": 131, "lloc": 100, "sloc": 100, "comments": 0, "multi": 0, "blank": 31, "single_comments": 0}, "aiohttp/tests/test_web_runner.py": {"loc": 192, "lloc": 131, "sloc": 139, "comments": 0, "multi": 0, "blank": 53, "single_comments": 0}, "aiohttp/tests/test_run_app.py": {"loc": 723, "lloc": 344, "sloc": 589, "comments": 7, "multi": 0, "blank": 129, "single_comments": 5}, "aiohttp/tests/test_pytest_plugin.py": {"loc": 257, "lloc": 40, "sloc": 175, "comments": 1, "multi": 0, "blank": 81, "single_comments": 1}, "aiohttp/tests/test_web_websocket.py": {"loc": 412, "lloc": 288, "sloc": 296, "comments": 0, "multi": 0, "blank": 116, "single_comments": 0}, "aiohttp/tests/test_multipart_helpers.py": {"loc": 662, "lloc": 508, "sloc": 552, "comments": 2, "multi": 0, "blank": 108, "single_comments": 2}, "aiohttp/tests/conftest.py": {"loc": 196, "lloc": 115, "sloc": 134, "comments": 20, "multi": 0, "blank": 44, "single_comments": 18}, "aiohttp/tests/test_web_middleware.py": {"loc": 432, "lloc": 224, "sloc": 366, "comments": 2, "multi": 0, "blank": 64, "single_comments": 2}, "aiohttp/tests/test_resolver.py": {"loc": 165, "lloc": 113, "sloc": 118, "comments": 4, "multi": 0, "blank": 43, "single_comments": 4}, "aiohttp/tests/test_cookiejar.py": {"loc": 681, "lloc": 274, "sloc": 519, "comments": 17, "multi": 0, "blank": 145, "single_comments": 17}, "aiohttp/tests/test_payload.py": {"loc": 112, "lloc": 74, "sloc": 74, "comments": 0, "multi": 0, "blank": 38, "single_comments": 0}, "aiohttp/tests/test_web_response.py": {"loc": 1133, "lloc": 742, "sloc": 790, "comments": 4, "multi": 0, "blank": 339, "single_comments": 4}, "aiohttp/tests/test_connector.py": {"loc": 2292, "lloc": 1440, "sloc": 1720, "comments": 33, "multi": 0, "blank": 542, "single_comments": 30}, "aiohttp/tests/test_client_response.py": {"loc": 1156, "lloc": 491, "sloc": 968, "comments": 5, "multi": 0, "blank": 184, "single_comments": 4}, "aiohttp/tests/test_base_protocol.py": {"loc": 182, "lloc": 140, "sloc": 140, "comments": 0, "multi": 0, "blank": 42, "single_comments": 0}, "aiohttp/tests/test_websocket_parser.py": {"loc": 503, "lloc": 315, "sloc": 362, "comments": 6, "multi": 0, "blank": 139, "single_comments": 2}, "aiohttp/tests/test_web_log.py": {"loc": 252, "lloc": 151, "sloc": 205, "comments": 1, "multi": 0, "blank": 47, "single_comments": 0}, "aiohttp/tests/test_websocket_writer.py": {"loc": 108, "lloc": 68, "sloc": 75, "comments": 1, "multi": 0, "blank": 32, "single_comments": 1}, "aiohttp/tests/test_multipart.py": {"loc": 1424, "lloc": 800, "sloc": 1219, "comments": 6, "multi": 0, "blank": 200, "single_comments": 5}, "aiohttp/tests/test_client_session.py": {"loc": 702, "lloc": 411, "sloc": 539, "comments": 12, "multi": 0, "blank": 151, "single_comments": 12}, "aiohttp/tests/test_web_sendfile.py": {"loc": 131, "lloc": 81, "sloc": 96, "comments": 0, "multi": 0, "blank": 35, "single_comments": 0}, "aiohttp/tests/test_urldispatch.py": {"loc": 1289, "lloc": 862, "sloc": 957, "comments": 7, "multi": 0, "blank": 327, "single_comments": 5}, "aiohttp/tests/test_web_sendfile_functional.py": {"loc": 815, "lloc": 561, "sloc": 586, "comments": 18, "multi": 0, "blank": 212, "single_comments": 17}, "aiohttp/tests/test_http_parser.py": {"loc": 1049, "lloc": 690, "sloc": 785, "comments": 16, "multi": 0, "blank": 248, "single_comments": 16}, "aiohttp/tests/test_proxy_functional.py": {"loc": 650, "lloc": 419, "sloc": 450, "comments": 7, "multi": 0, "blank": 193, "single_comments": 7}, "aiohttp/tests/test_client_functional.py": {"loc": 2954, "lloc": 2068, "sloc": 2120, "comments": 31, "multi": 0, "blank": 809, "single_comments": 25}, "aiohttp/tests/test_client_request.py": {"loc": 1142, "lloc": 717, "sloc": 830, "comments": 4, "multi": 0, "blank": 308, "single_comments": 4}, "aiohttp/tests/test_tracing.py": {"loc": 164, "lloc": 47, "sloc": 150, "comments": 0, "multi": 0, "blank": 14, "single_comments": 0}, "aiohttp/tests/test_client_ws_functional.py": {"loc": 893, "lloc": 640, "sloc": 645, "comments": 3, "multi": 0, "blank": 245, "single_comments": 3}, "aiohttp/tests/test_websocket_handshake.py": {"loc": 266, "lloc": 158, "sloc": 180, "comments": 4, "multi": 0, "blank": 82, "single_comments": 4}, "aiohttp/tests/autobahn/client.py": {"loc": 51, "lloc": 39, "sloc": 39, "comments": 1, "multi": 0, "blank": 11, "single_comments": 1}, "aiohttp/tests/autobahn/server.py": {"loc": 57, "lloc": 40, "sloc": 41, "comments": 1, "multi": 0, "blank": 15, "single_comments": 1}, "aiohttp/tools/bench-asyncio-write.py": {"loc": 118, "lloc": 73, "sloc": 101, "comments": 1, "multi": 0, "blank": 17, "single_comments": 0}, "aiohttp/tools/gen.py": {"loc": 162, "lloc": 84, "sloc": 128, "comments": 3, "multi": 0, "blank": 31, "single_comments": 3}, "aiohttp/tools/check_changes.py": {"loc": 49, "lloc": 33, "sloc": 37, "comments": 1, "multi": 0, "blank": 11, "single_comments": 1}}
