{"arxiv-sanity-preserver/download_pdfs.py": {"loc": 44, "lloc": 36, "sloc": 35, "comments": 3, "multi": 0, "blank": 8, "single_comments": 1}, "arxiv-sanity-preserver/fetch_papers.py": {"loc": 124, "lloc": 84, "sloc": 83, "comments": 11, "multi": 13, "blank": 19, "single_comments": 9}, "arxiv-sanity-preserver/buildsvm.py": {"loc": 66, "lloc": 48, "sloc": 44, "comments": 12, "multi": 0, "blank": 14, "single_comments": 8}, "arxiv-sanity-preserver/make_cache.py": {"loc": 103, "lloc": 81, "sloc": 77, "comments": 11, "multi": 6, "blank": 15, "single_comments": 5}, "arxiv-sanity-preserver/parse_pdf_to_text.py": {"loc": 48, "lloc": 29, "sloc": 28, "comments": 7, "multi": 6, "blank": 11, "single_comments": 3}, "arxiv-sanity-preserver/utils.py": {"loc": 101, "lloc": 55, "sloc": 52, "comments": 14, "multi": 20, "blank": 17, "single_comments": 12}, "arxiv-sanity-preserver/thumb_pdf.py": {"loc": 86, "lloc": 50, "sloc": 47, "comments": 26, "multi": 4, "blank": 14, "single_comments": 21}, "arxiv-sanity-preserver/analyze.py": {"loc": 101, "lloc": 75, "sloc": 76, "comments": 22, "multi": 4, "blank": 13, "single_comments": 8}, "arxiv-sanity-preserver/serve.py": {"loc": 714, "lloc": 543, "sloc": 528, "comments": 108, "multi": 0, "blank": 101, "single_comments": 85}, "arxiv-sanity-preserver/twitter_daemon.py": {"loc": 189, "lloc": 143, "sloc": 132, "comments": 45, "multi": 4, "blank": 29, "single_comments": 24}}
