{"toapi/setup.py": {"loc": 44, "lloc": 8, "sloc": 40, "comments": 0, "multi": 0, "blank": 4, "single_comments": 0}, "toapi/examples/hackernews_page.py": {"loc": 28, "lloc": 19, "sloc": 19, "comments": 0, "multi": 0, "blank": 9, "single_comments": 0}, "toapi/examples/click/app.py": {"loc": 14, "lloc": 9, "sloc": 8, "comments": 0, "multi": 0, "blank": 6, "single_comments": 0}, "toapi/toapi/log.py": {"loc": 34, "lloc": 15, "sloc": 15, "comments": 0, "multi": 10, "blank": 9, "single_comments": 0}, "toapi/toapi/cli.py": {"loc": 11, "lloc": 7, "sloc": 5, "comments": 0, "multi": 3, "blank": 3, "single_comments": 0}, "toapi/toapi/item.py": {"loc": 43, "lloc": 33, "sloc": 33, "comments": 0, "multi": 0, "blank": 10, "single_comments": 0}, "toapi/toapi/api.py": {"loc": 132, "lloc": 108, "sloc": 105, "comments": 0, "multi": 0, "blank": 27, "single_comments": 0}, "toapi/toapi/__init__.py": {"loc": 4, "lloc": 3, "sloc": 3, "comments": 0, "multi": 0, "blank": 1, "single_comments": 0}, "toapi/tests/test_toapi.py": {"loc": 51, "lloc": 40, "sloc": 40, "comments": 0, "multi": 0, "blank": 11, "single_comments": 0}}
